setup.cfg
setup.py
keyringcookiejar/__init__.py
keyringcookiejar.egg-info/PKG-INFO
keyringcookiejar.egg-info/SOURCES.txt
keyringcookiejar.egg-info/dependency_links.txt
keyringcookiejar.egg-info/requires.txt
keyringcookiejar.egg-info/top_level.txt