Metadata-Version: 1.1
Name: keyringcookiejar
Version: 0.1
Summary: Store cookies using the keyring package
Home-page: https://github.com/tmaher/keyringcookiejar
Author: Tom Maher
Author-email: tmaher@pw0n.me
License: UNKNOWN
Download-URL: https://github.com/tmaher/keyringcookiejar/tarball/0.1
Platform: UNKNOWN
